LICENSE.txt
README.md
setup.cfg
setup.py
EasyReqAJM/EasyReqAJM.py
EasyReqAJM/__init__.py
EasyReqAJM.egg-info/PKG-INFO
EasyReqAJM.egg-info/SOURCES.txt
EasyReqAJM.egg-info/dependency_links.txt
EasyReqAJM.egg-info/top_level.txt