Metadata-Version: 2.1
Name: EasyReqAJM
Version: 0.1
Summary: Wrapper for Requests module to make my life easier.
Home-page: https://github.com/amcsparron2793-Water/EasyReqAJM
Download-URL: https://github.com/amcsparron2793-Water/EasyReqAJM/archive/refs/tags/0.1.tar.gz
Author: Amcsparron
Author-email: amcsparron@albanyny.gov
License: MIT License
License-File: LICENSE.txt
